pure_requests/__init__.py
pure_requests/_bug.py
pure_requests/basic.py
pure_requests/py.typed
pure_requests/rate_limit.py
pure_requests/response.py
pure_requests/retry.py
pure_requests-3.0.0.dist-info/WHEEL
pure_requests-3.0.0.dist-info/METADATA
pure_requests-3.0.0.dist-info/RECORD
