Metadata-Version: 2.4
Name: pure_requests
Version: 3.0.0
Summary: Wrapper over requests library for functional programming
Author-email: Product Team <development@fluidattacks.com>
Requires-Python: >=3.11
Classifier: License :: OSI Approved :: MIT License
Requires-Dist: Deprecated >=1.2.18, <2.0.0
Requires-Dist: requests >=2.32.5, <3.0.0
Requires-Dist: fa-purity >=2.5.2, <3.0.0
